jsbuild.py
js_build_cli-0.0.6.dist-info/LICENSE.txt
js_build_cli-0.0.6.dist-info/METADATA
js_build_cli-0.0.6.dist-info/WHEEL
js_build_cli-0.0.6.dist-info/entry_points.txt
js_build_cli-0.0.6.dist-info/top_level.txt
js_build_cli-0.0.6.dist-info/RECORD
