Metadata-Version: 2.1
Name: js-build-cli
Version: 0.0.6
Summary: Low bandwidth DoS tool. Slowloris rewrite in Python.
Home-page: https://github.com/gkbrk/jsbuild
Author: Gokberk Yaltirakli
Author-email: opensource@gkbrk.com
License: Apache License 2.0
Keywords: javascript,build,package,minify,uglify
License-File: LICENSE.txt
